unpack200.cp36-win32.pyd
unpack200-1.0.1.dist-info/METADATA
unpack200-1.0.1.dist-info/RECORD
unpack200-1.0.1.dist-info/WHEEL
unpack200-1.0.1.dist-info/top_level.txt
