Metadata-Version: 2.1
Name: unpack200
Version: 1.0.1
Summary: A Python wrapper for the JDK unpack200 utility
Home-page: https://github.com/tfff1OFFICIAL/PythonUnpack200/
Author: tfff1
License: MIT
Project-URL: Source, https://github.com/tfff1OFFICIAL/PythonUnpack200/
Keywords: pack pack200 java packfile
Platform: UNKNOWN
Classifier: License :: OSI Approved :: MIT License
Classifier: Programming Language :: Python :: 3.6
Requires-Python: >=3
